plover_michela/__init__.py
plover_michela/machine.py
plover_michela/system.py
plover_michela/assets/italian_words.txt
plover_michela/assets/michela_numeri.json
plover_michela/assets/michela_principale.json
plover_michela/assets/michela_punteggiaturacomandi.json
plover_michela/assets/michela_sillabico.json
plover_michela/assets/michela_utente.json
plover_michela-2.0.0.dist-info/METADATA
plover_michela-2.0.0.dist-info/WHEEL
plover_michela-2.0.0.dist-info/entry_points.txt
plover_michela-2.0.0.dist-info/top_level.txt
plover_michela-2.0.0.dist-info/zip-safe
plover_michela-2.0.0.dist-info/RECORD
