Metadata-Version: 2.1
Name: plover-michela
Version: 2.0.0
Summary: Michela (Italian system) support for Plover
Home-page: https://github.com/benoit-pierre/plover_michela
Author: Benoit Pierre
Author-email: benoit.pierre@gmail.com
License: GNU General Public License v2 or later (GPLv2+)
Project-URL: Documentation, https://github.com/Sillabix/Plover-Michela
Project-URL: Source Code, https://github.com/benoit-pierre/plover_michela
Project-URL: Issue Tracker, https://github.com/benoit-pierre/plover_michela/issues
Keywords: plover plover_plugin
Classifier: Development Status :: 4 - Beta
Classifier: Environment :: Plugins
Classifier: Intended Audience :: End Users/Desktop
Classifier: License :: OSI Approved :: GNU General Public License v2 or later (GPLv2+)
Classifier: Operating System :: OS Independent
Classifier: Programming Language :: Python :: 3
Classifier: Programming Language :: Python :: 3.6
Classifier: Programming Language :: Python :: 3.7
Classifier: Programming Language :: Python :: 3.8
Classifier: Programming Language :: Python :: 3.9
Classifier: Programming Language :: Python :: 3.10
Requires-Python: >=3.6
Requires-Dist: plover (>=4.0.0.dev1)
Requires-Dist: plover-midi (>=0.2.6)
Provides-Extra: test
Requires-Dist: libcst ; extra == 'test'
Requires-Dist: pytest ; extra == 'test'
